myprojectreda/.gitignore
myprojectreda/.readthedocs.yml
myprojectreda/CHANGELOG.md
myprojectreda/CONDUCT.md
myprojectreda/CONTRIBUTING.md
myprojectreda/LICENSE
myprojectreda/README.md
myprojectreda/docs/Makefile
myprojectreda/docs/changelog.md
myprojectreda/docs/conduct.md
myprojectreda/docs/conf.py
myprojectreda/docs/contributing.md
myprojectreda/docs/example.ipynb
myprojectreda/docs/index.md
myprojectreda/docs/make.bat
myprojectreda/docs/requirements.txt
myprojectreda/pyproject.toml
myprojectreda/src/myprojectreda/__init__.py
myprojectreda/src/myprojectreda/myprojectreda.py
myprojectreda/tests/test_myprojectreda.py
myprojectreda-0.0.1.dist-info/LICENSE
myprojectreda-0.0.1.dist-info/METADATA
myprojectreda-0.0.1.dist-info/WHEEL
myprojectreda-0.0.1.dist-info/RECORD
