Metadata-Version: 2.3
Name: myprojectreda
Version: 0.0.1
Summary: python project
License: MIT
Author: Reda El Fassi
Requires-Python: >=3.12,<4.0
Classifier: License :: OSI Approved :: MIT License
Classifier: Programming Language :: Python :: 3
Classifier: Programming Language :: Python :: 3.12
Classifier: Programming Language :: Python :: 3.13
